[
    {
        "subject": "Логістика та управління ланцюгами поставок: поширення європейського досвіду",
        "lecturer": "Чорнописька Н.В., ",
        "location": " Практична",
        "url": "https://us02web.zoom.us/j/89730711344?pwd=dVBjZlVrenhFelV1NEFNUjdBNm5TQT09%20%20Meeting%20ID:%20897%203071%201344%20Passcode:%207i5Ctz",
        "type": "practical",
        "isFirstWeek": true,
        "isSecondWeek": false,
        "isFirstSubgroup": true,
        "isSecondSubgroup": true,
        "day": 1,
        "number": 3
    },
    {
        "subject": "Логістика та управління ланцюгами поставок: поширення європейського досвіду",
        "lecturer": "Чорнописька Н.В., ",
        "location": " Лекція",
        "url": "https://us02web.zoom.us/j/89730711344?pwd=dVBjZlVrenhFelV1NEFNUjdBNm5TQT09%20%20Meeting%20ID:%20897%203071%201344%20Passcode:%207i5Ctz",
        "type": "lection",
        "isFirstWeek": true,
        "isSecondWeek": false,
        "isFirstSubgroup": true,
        "isSecondSubgroup": true,
        "day": 2,
        "number": 6
    }
]