[
    {
        "subject": "Теорія кольору та кольороутворення",
        "lecturer": "Лотошинська Н.Д., ",
        "location": " Лекція",
        "url": "https://us04web.zoom.us/j/78671243673?pwd=Rk1HWlppSkJxMUxqSjJIRWxuUkJBZz09",
        "type": "lection",
        "isFirstWeek": true,
        "isSecondWeek": true,
        "isFirstSubgroup": true,
        "isSecondSubgroup": true,
        "day": 1,
        "number": 2
    },
    {
        "subject": "Теорія кольору та кольороутворення",
        "lecturer": "Лотошинська Н.Д., ",
        "location": " Лекція",
        "url": "https://us04web.zoom.us/j/79095490577?pwd=Umc0QlF6WjNXMVlxdnRqQnBZT2c2QT09",
        "type": "lection",
        "isFirstWeek": true,
        "isSecondWeek": false,
        "isFirstSubgroup": true,
        "isSecondSubgroup": true,
        "day": 1,
        "number": 3
    },
    {
        "subject": "Об`єктно-орієнтоване програмування, частина 2",
        "lecturer": "Кинаш Ю.Є., ",
        "location": " Лекція",
        "url": "https://meet.google.com/yai-gzsi-dtf",
        "type": "lection",
        "isFirstWeek": false,
        "isSecondWeek": true,
        "isFirstSubgroup": true,
        "isSecondSubgroup": true,
        "day": 1,
        "number": 3
    },
    {
        "subject": "Додрукарське опрацювання інформації",
        "lecturer": "Сеньківська Н.Є., ",
        "location": ", Лабораторна",
        "url": "https://us04web.zoom.us/j/76707663446?pwd=V2h4b2Fqb21pbVR3bE5GUWQ3YzNCdz09",
        "type": "lab",
        "isFirstWeek": true,
        "isSecondWeek": true,
        "isFirstSubgroup": false,
        "isSecondSubgroup": true,
        "day": 2,
        "number": 2
    },
    {
        "subject": "Об`єктно-орієнтоване програмування, частина 2",
        "lecturer": "Кустра Н.О., ",
        "location": ", Лабораторна",
        "url": "https://meet.google.com/yai-gzsi-dtf",
        "type": "lab",
        "isFirstWeek": true,
        "isSecondWeek": true,
        "isFirstSubgroup": false,
        "isSecondSubgroup": true,
        "day": 2,
        "number": 3
    },
    {
        "subject": "Інформаційне забезпечення та технології у видавничо-друкарській справі, частина 2",
        "lecturer": "Марцишин Р.С., ",
        "location": ", Лабораторна",
        "url": "https://meet.google.com/utw-utuv-osv",
        "type": "lab",
        "isFirstWeek": true,
        "isSecondWeek": true,
        "isFirstSubgroup": false,
        "isSecondSubgroup": true,
        "day": 2,
        "number": 4
    },
    {
        "subject": "Об`єктно-орієнтоване програмування, частина 2",
        "lecturer": "Кустра Н.О., ",
        "location": " Лабораторна",
        "url": "https://meet.google.com/yai-gzsi-dtf",
        "type": "lab",
        "isFirstWeek": true,
        "isSecondWeek": true,
        "isFirstSubgroup": true,
        "isSecondSubgroup": false,
        "day": 2,
        "number": 4
    },
    {
        "subject": "Інформаційне забезпечення та технології у видавничо-друкарській справі, частина 2",
        "lecturer": "Марцишин Р.С., ",
        "location": " Лабораторна",
        "url": "https://meet.google.com/utw-utuv-osv",
        "type": "lab",
        "isFirstWeek": true,
        "isSecondWeek": true,
        "isFirstSubgroup": true,
        "isSecondSubgroup": false,
        "day": 2,
        "number": 5
    },
    {
        "subject": "Об`єктно-орієнтоване програмування, частина 2",
        "lecturer": "Кинаш Ю.Є., ",
        "location": " Лекція",
        "url": "https://meet.google.com/yai-gzsi-dtf",
        "type": "lection",
        "isFirstWeek": true,
        "isSecondWeek": true,
        "isFirstSubgroup": true,
        "isSecondSubgroup": true,
        "day": 3,
        "number": 2
    },
    {
        "subject": "Додрукарське опрацювання інформації",
        "lecturer": "Лотошинська Н.Д., ",
        "location": " Лекція",
        "url": "https://us04web.zoom.us/j/73578706335?pwd=L3hCcENxQU1NRW9FS3dZOTBjZnlwQT09",
        "type": "lection",
        "isFirstWeek": true,
        "isSecondWeek": true,
        "isFirstSubgroup": true,
        "isSecondSubgroup": true,
        "day": 3,
        "number": 3
    },
    {
        "subject": "Додрукарське опрацювання інформації",
        "lecturer": "Сеньківська Н.Є., ",
        "location": " Лабораторна",
        "url": "https://us04web.zoom.us/j/73789825173?pwd=SzdNVVFxRm93RDB1dEJ3UWxURUYzdz09",
        "type": "lab",
        "isFirstWeek": true,
        "isSecondWeek": true,
        "isFirstSubgroup": true,
        "isSecondSubgroup": false,
        "day": 4,
        "number": 1
    },
    {
        "subject": "Теорія кольору та кольороутворення",
        "lecturer": "Лотошинська Н.Д., ",
        "location": " Лабораторна",
        "url": "https://us04web.zoom.us/j/75650148211?pwd=bFVrRUYzeGRHVklPUzRpai9hb1E4UT09",
        "type": "lab",
        "isFirstWeek": true,
        "isSecondWeek": true,
        "isFirstSubgroup": true,
        "isSecondSubgroup": false,
        "day": 4,
        "number": 2
    },
    {
        "subject": "Основи цифрової обробки сигналів",
        "lecturer": "Кинаш Ю.Є., ",
        "location": " Лабораторна",
        "url": "https://meet.google.com/yai-gzsi-dtf",
        "type": "lab",
        "isFirstWeek": true,
        "isSecondWeek": true,
        "isFirstSubgroup": true,
        "isSecondSubgroup": false,
        "day": 4,
        "number": 3
    },
    {
        "subject": "Теорія кольору та кольороутворення",
        "lecturer": "Лотошинська Н.Д., ",
        "location": ", Лабораторна",
        "url": "https://us04web.zoom.us/j/73571680097?pwd=NFZ2cWFjZlJqeEVnZmtIdnVaVitPUT09",
        "type": "lab",
        "isFirstWeek": true,
        "isSecondWeek": true,
        "isFirstSubgroup": false,
        "isSecondSubgroup": true,
        "day": 4,
        "number": 3
    },
    {
        "subject": "Основи цифрової обробки сигналів",
        "lecturer": "Кинаш Ю.Є., ",
        "location": ", Лабораторна",
        "url": "https://meet.google.com/yai-gzsi-dtf",
        "type": "lab",
        "isFirstWeek": true,
        "isSecondWeek": true,
        "isFirstSubgroup": false,
        "isSecondSubgroup": true,
        "day": 4,
        "number": 4
    },
    {
        "subject": "Основи цифрової обробки сигналів",
        "lecturer": "Рашкевич Ю.М., ",
        "location": " Лекція",
        "url": "https://meet.google.com/qxq-wyzj-moc",
        "type": "lection",
        "isFirstWeek": true,
        "isSecondWeek": true,
        "isFirstSubgroup": true,
        "isSecondSubgroup": true,
        "day": 5,
        "number": 1
    },
    {
        "subject": "Інформаційне забезпечення та технології у видавничо-друкарській справі, частина 2",
        "lecturer": "Марцишин Р.С., ",
        "location": " Лекція",
        "url": "https://meet.google.com/utw-utuv-osv",
        "type": "lection",
        "isFirstWeek": true,
        "isSecondWeek": true,
        "isFirstSubgroup": true,
        "isSecondSubgroup": true,
        "day": 5,
        "number": 2
    }
]