[
    {
        "subject": "Основи охорони праці та безпека життєдіяльності",
        "lecturer": "Мацьків О.О., ",
        "location": " Лабораторна",
        "url": "https://teams.microsoft.com/l/channel/19%3a35d02248a8774e15b739c711aeede774%40thread.tacv2/%25D0%2597%25D0%25B0%25D0%25B3%25D0%25B0%25D0%25BB%25D1%258C%25D0%25BD%25D0%25B5?groupId=3462c2cb-f122-491b-8679-2501f3814e78&tenantId=7631cd62-5187-4e15-8b8e-ef653e366e7a",
        "type": "lab",
        "isFirstWeek": true,
        "isSecondWeek": false,
        "isFirstSubgroup": true,
        "isSecondSubgroup": false,
        "day": 2,
        "number": 3
    },
    {
        "subject": "Обробка зображень методами штучного інтелекту",
        "lecturer": "Пелешко Д.Д., ",
        "location": ", Лабораторна",
        "url": "https://us02web.zoom.us/meeting/tZ0kdOyvrD4sHdeGY2xxMVpAvRPh6BVQi0rK/ics?icsToken=98tyKuGhpzgvHdaQth6ERpx5HYjCZ-3zpiVdgqdYuya3Gzh-VBPXINByOuRdJunZ",
        "type": "lab",
        "isFirstWeek": true,
        "isSecondWeek": true,
        "isFirstSubgroup": false,
        "isSecondSubgroup": true,
        "day": 2,
        "number": 3
    },
    {
        "subject": "Обробка зображень методами штучного інтелекту",
        "lecturer": "Пелешко Д.Д., ",
        "location": " Лабораторна",
        "url": "https://us02web.zoom.us/meeting/tZcrf-uorz4iG9Wjh53JIS-D6iflApaIJG11/ics?icsToken=98tyKuGrqDMoGtWQuBiGRpwqBIqga_TzmCVHjfpqlhewUAp6UU7SYOtEPpNvEfH6",
        "type": "lab",
        "isFirstWeek": true,
        "isSecondWeek": true,
        "isFirstSubgroup": true,
        "isSecondSubgroup": false,
        "day": 2,
        "number": 4
    },
    {
        "subject": "Обробка мови методами штучного інтелекту",
        "lecturer": "Сивоконь О.О., ",
        "location": ", Лабораторна",
        "url": "https://grammarly.zoom.us/j/94225223189?pwd=alVrU1BsOEZocFRVU0hrNTJMS2gyUT09",
        "type": "lab",
        "isFirstWeek": true,
        "isSecondWeek": true,
        "isFirstSubgroup": false,
        "isSecondSubgroup": true,
        "day": 2,
        "number": 4
    },
    {
        "subject": "Основи охорони праці та безпека життєдіяльності",
        "lecturer": "Мацьків О.О., ",
        "location": ", Лабораторна",
        "url": "https://teams.microsoft.com/l/channel/19%3a35d02248a8774e15b739c711aeede774%40thread.tacv2/%25D0%2597%25D0%25B0%25D0%25B3%25D0%25B0%25D0%25BB%25D1%258C%25D0%25BD%25D0%25B5?groupId=3462c2cb-f122-491b-8679-2501f3814e78&tenantId=7631cd62-5187-4e15-8b8e-ef653e366e7a",
        "type": "lab",
        "isFirstWeek": false,
        "isSecondWeek": true,
        "isFirstSubgroup": false,
        "isSecondSubgroup": true,
        "day": 2,
        "number": 5
    },
    {
        "subject": "Обробка мови методами штучного інтелекту",
        "lecturer": "Сивоконь О.О., ",
        "location": " Лабораторна",
        "url": "https://grammarly.zoom.us/j/94225223189?pwd=alVrU1BsOEZocFRVU0hrNTJMS2gyUT09",
        "type": "lab",
        "isFirstWeek": true,
        "isSecondWeek": true,
        "isFirstSubgroup": true,
        "isSecondSubgroup": false,
        "day": 2,
        "number": 5
    },
    {
        "subject": "Основи робототехніки",
        "lecturer": "Гасько Р.Т., ",
        "location": ", Лабораторна",
        "url": "https://meet.google.com/jvj-obwr-krn",
        "type": "lab",
        "isFirstWeek": true,
        "isSecondWeek": true,
        "isFirstSubgroup": false,
        "isSecondSubgroup": true,
        "day": 3,
        "number": 2
    },
    {
        "subject": "Основи робототехніки",
        "lecturer": "Гасько Р.Т., ",
        "location": " Лабораторна",
        "url": "https://meet.google.com/jvj-obwr-krn",
        "type": "lab",
        "isFirstWeek": true,
        "isSecondWeek": true,
        "isFirstSubgroup": true,
        "isSecondSubgroup": false,
        "day": 3,
        "number": 3
    },
    {
        "subject": "Основи охорони праці та безпека життєдіяльності",
        "lecturer": "Мацьків О.О., ",
        "location": " Практична",
        "url": "https://teams.microsoft.com/l/channel/19%3a35d02248a8774e15b739c711aeede774%40thread.tacv2/%25D0%2597%25D0%25B0%25D0%25B3%25D0%25B0%25D0%25BB%25D1%258C%25D0%25BD%25D0%25B5?groupId=3462c2cb-f122-491b-8679-2501f3814e78&tenantId=7631cd62-5187-4e15-8b8e-ef653e366e7a",
        "type": "practical",
        "isFirstWeek": false,
        "isSecondWeek": true,
        "isFirstSubgroup": true,
        "isSecondSubgroup": true,
        "day": 3,
        "number": 4
    },
    {
        "subject": "Обробка мови методами штучного інтелекту",
        "lecturer": "Сивоконь О.О., ",
        "location": " Лекція",
        "url": "https://grammarly.zoom.us/j/98016906104?pwd=NjhwT2wxYVI2ZzFVWEtrZ0dDeDRYZz09",
        "type": "lection",
        "isFirstWeek": true,
        "isSecondWeek": true,
        "isFirstSubgroup": true,
        "isSecondSubgroup": true,
        "day": 4,
        "number": 2
    },
    {
        "subject": "Обробка зображень методами штучного інтелекту",
        "lecturer": "Пелешко Д.Д., ",
        "location": " Лекція",
        "url": "https://us02web.zoom.us/meeting/tZckcO2rpj0iEtVm93str7rCmvHV1q01Pe-f/ics?icsToken=98tyKuGrpzwuGdyTuBGGRpwqHY_CLOnxiCFHj7drkUa2EDRBNRHVO_RqBONuQIng",
        "type": "lection",
        "isFirstWeek": true,
        "isSecondWeek": true,
        "isFirstSubgroup": true,
        "isSecondSubgroup": true,
        "day": 4,
        "number": 3
    },
    {
        "subject": "Основи охорони праці та безпека життєдіяльності",
        "lecturer": "Мацьків О.О., ",
        "location": " Лекція",
        "url": "https://teams.microsoft.com/l/channel/19%3a35d02248a8774e15b739c711aeede774%40thread.tacv2/%25D0%2597%25D0%25B0%25D0%25B3%25D0%25B0%25D0%25BB%25D1%258C%25D0%25BD%25D0%25B5?groupId=3462c2cb-f122-491b-8679-2501f3814e78&tenantId=7631cd62-5187-4e15-8b8e-ef653e366e7a",
        "type": "lection",
        "isFirstWeek": true,
        "isSecondWeek": true,
        "isFirstSubgroup": true,
        "isSecondSubgroup": true,
        "day": 4,
        "number": 4
    },
    {
        "subject": "Обробка зображень методами штучного інтелекту",
        "lecturer": "Пелешко Д.Д., ",
        "location": " Лекція",
        "url": "https://us02web.zoom.us/meeting/tZckcO2rpj0iEtVm93str7rCmvHV1q01Pe-f/ics?icsToken=98tyKuGrpzwuGdyTuBGGRpwqHY_CLOnxiCFHj7drkUa2EDRBNRHVO_RqBONuQIng",
        "type": "lection",
        "isFirstWeek": true,
        "isSecondWeek": true,
        "isFirstSubgroup": true,
        "isSecondSubgroup": true,
        "day": 5,
        "number": 2
    },
    {
        "subject": "Основи робототехніки",
        "lecturer": "Гасько Р.Т., ",
        "location": " Лекція",
        "url": "https://meet.google.com/jvj-obwr-krn",
        "type": "lection",
        "isFirstWeek": true,
        "isSecondWeek": true,
        "isFirstSubgroup": true,
        "isSecondSubgroup": true,
        "day": 5,
        "number": 3
    },
    {
        "subject": "Основи робототехніки",
        "lecturer": "Гасько Р.Т., ",
        "location": " Лекція",
        "url": "https://meet.google.com/jvj-obwr-krn",
        "type": "lection",
        "isFirstWeek": true,
        "isSecondWeek": true,
        "isFirstSubgroup": true,
        "isSecondSubgroup": true,
        "day": 5,
        "number": 4
    }
]