[
    {
        "subject": "Технології машинного навчання в кіберфізичних системах",
        "lecturer": "Бочкарьов О.Ю., ",
        "location": " Лекція",
        "url": "https://us02web.zoom.us/j/87018816679?pwd=OVhUWk56eG4wTm5tSmVMaExrL1Jkdz09",
        "type": "lection",
        "isFirstWeek": true,
        "isSecondWeek": true,
        "isFirstSubgroup": true,
        "isSecondSubgroup": true,
        "day": 2,
        "number": 3
    },
    {
        "subject": "Дослідження і проектування програмних систем",
        "lecturer": "Березко Л.О., ",
        "location": " Лекція",
        "url": "https://meet.google.com/vhy-ntcf-cjr",
        "type": "lection",
        "isFirstWeek": true,
        "isSecondWeek": true,
        "isFirstSubgroup": true,
        "isSecondSubgroup": true,
        "day": 2,
        "number": 4
    },
    {
        "subject": "Дослідження і проектування програмних систем",
        "lecturer": "Березко Л.О., ",
        "location": " Лекція",
        "url": "https://meet.google.com/vhy-ntcf-cjr",
        "type": "lection",
        "isFirstWeek": true,
        "isSecondWeek": false,
        "isFirstSubgroup": true,
        "isSecondSubgroup": true,
        "day": 2,
        "number": 5
    },
    {
        "subject": "Проектування комп`ютерних засобів обробки сигналів і зображень",
        "lecturer": "Ваврук Є.Я., ",
        "location": " Лекція",
        "url": "https://zoom.us/j/93092614715?pwd=SXArM0g0aXM2TE1VcU82a3lzZ2hkZz09",
        "type": "lection",
        "isFirstWeek": true,
        "isSecondWeek": true,
        "isFirstSubgroup": true,
        "isSecondSubgroup": true,
        "day": 3,
        "number": 3
    },
    {
        "subject": "Проектування засобів мобільних та хмарних обчислень в кіберфізичних системах",
        "lecturer": "Морозов Ю.В., ",
        "location": " Лекція",
        "url": "https://us02web.zoom.us/j/85074712048?pwd=eXFueG5RWWQ3SVl4K083d0kwek1MQT09",
        "type": "lection",
        "isFirstWeek": true,
        "isSecondWeek": true,
        "isFirstSubgroup": true,
        "isSecondSubgroup": true,
        "day": 3,
        "number": 4
    },
    {
        "subject": "Дослідження і проектування інтерфейсів користувача",
        "lecturer": "Березко Л.О., ",
        "location": " Лекція",
        "url": "https://meet.google.com/uba-ebsn-kwe",
        "type": "lection",
        "isFirstWeek": true,
        "isSecondWeek": true,
        "isFirstSubgroup": true,
        "isSecondSubgroup": true,
        "day": 3,
        "number": 5
    },
    {
        "subject": "Технології машинного навчання в кіберфізичних системах",
        "lecturer": "Муляревич О.В., ",
        "location": " Лабораторна",
        "url": "https://zoom.us/j/4442828220?pwd=cENhcyt1VWhTZUVab3ZNOUprVGxQQT09",
        "type": "lab",
        "isFirstWeek": false,
        "isSecondWeek": true,
        "isFirstSubgroup": true,
        "isSecondSubgroup": true,
        "day": 4,
        "number": 2
    },
    {
        "subject": "Фахова іноземна мова",
        "lecturer": "Балацька Л.П., ",
        "location": " Практична",
        "url": "https://join.skype.com/jKO7IkMkWoPt",
        "type": "practical",
        "isFirstWeek": true,
        "isSecondWeek": true,
        "isFirstSubgroup": true,
        "isSecondSubgroup": true,
        "day": 4,
        "number": 4
    },
    {
        "subject": "Проектування комп`ютерних засобів обробки сигналів і зображень",
        "lecturer": "Наконечний Р.А., ",
        "location": " Лабораторна",
        "url": "https://zoom.us/j/9980603030?pwd=bFRZMWVoODRCR2U3RE5Lb2dkdFpTUT09",
        "type": "lab",
        "isFirstWeek": true,
        "isSecondWeek": true,
        "isFirstSubgroup": true,
        "isSecondSubgroup": true,
        "day": 4,
        "number": 5
    },
    {
        "subject": "Дослідження і проектування інтерфейсів користувача",
        "lecturer": "Костик А.Т., ",
        "location": ", Лабораторна",
        "url": "",
        "type": "lab",
        "isFirstWeek": true,
        "isSecondWeek": false,
        "isFirstSubgroup": false,
        "isSecondSubgroup": true,
        "day": 4,
        "number": 6
    },
    {
        "subject": "Дослідження і проектування програмних систем",
        "lecturer": "Пищак І.І., ",
        "location": " Лабораторна",
        "url": "https://us02web.zoom.us/j/6395142719?pwd=ZWJVSDdRdlNzbGJqeGJUNXJld01JZz09",
        "type": "lab",
        "isFirstWeek": true,
        "isSecondWeek": false,
        "isFirstSubgroup": true,
        "isSecondSubgroup": true,
        "day": 5,
        "number": 2
    },
    {
        "subject": "Проектування засобів мобільних та хмарних обчислень в кіберфізичних системах",
        "lecturer": "Морозов Ю.В., ",
        "location": " Лабораторна",
        "url": "https://us02web.zoom.us/j/85074712048?pwd=eXFueG5RWWQ3SVl4K083d0kwek1MQT09",
        "type": "lab",
        "isFirstWeek": true,
        "isSecondWeek": false,
        "isFirstSubgroup": true,
        "isSecondSubgroup": true,
        "day": 5,
        "number": 3
    }
]