[
    {
        "subject": "Управління експортно-імпортними операціями в умовах євроінтеграції",
        "lecturer": "Двуліт З.П., ",
        "location": " Практична",
        "url": "https://teams.microsoft.com/l/channel/19%3a85ee7aafa4fc431d8458928e0f66c1b1%40thread.tacv2/%25D0%2597%25D0%25B0%25D0%25B3%25D0%25B0%25D0%25BB%25D1%258C%25D0%25BD%25D0%25B5?groupId=21602e7b-231d-438e-a650-807725baf872&tenantId=7631cd62-5187-4e15-8b8e-ef653e366e7a",
        "type": "practical",
        "isFirstWeek": false,
        "isSecondWeek": true,
        "isFirstSubgroup": true,
        "isSecondSubgroup": true,
        "day": 1,
        "number": 2
    },
    {
        "subject": "Оподаткування зовнішньоекономічної діяльності",
        "lecturer": "Калиновський А.О., ",
        "location": " Лабораторна",
        "url": "https://teams.microsoft.com/l/channel/19%3acf5724ab47ce4f9889f4a20745a82ed8%40thread.tacv2/%25D0%2597%25D0%25B0%25D0%25B3%25D0%25B0%25D0%25BB%25D1%258C%25D0%25BD%25D0%25B5?groupId=c70d36e4-8c57-4ba9-8ad7-fef640051d76&tenantId=7631cd62-5187-4e15-8b8e-ef653e366e7a",
        "type": "lab",
        "isFirstWeek": false,
        "isSecondWeek": true,
        "isFirstSubgroup": true,
        "isSecondSubgroup": false,
        "day": 1,
        "number": 3
    },
    {
        "subject": "Оподаткування зовнішньоекономічної діяльності",
        "lecturer": "Калиновський А.О., ",
        "location": ", Лабораторна",
        "url": "https://teams.microsoft.com/l/channel/19%3acf5724ab47ce4f9889f4a20745a82ed8%40thread.tacv2/%25D0%2597%25D0%25B0%25D0%25B3%25D0%25B0%25D0%25BB%25D1%258C%25D0%25BD%25D0%25B5?groupId=c70d36e4-8c57-4ba9-8ad7-fef640051d76&tenantId=7631cd62-5187-4e15-8b8e-ef653e366e7a",
        "type": "lab",
        "isFirstWeek": true,
        "isSecondWeek": false,
        "isFirstSubgroup": false,
        "isSecondSubgroup": true,
        "day": 1,
        "number": 3
    },
    {
        "subject": "Маркетингові дослідження",
        "lecturer": "Капраль О.Р., ",
        "location": " Лабораторна",
        "url": "https://us02web.zoom.us/j/85365781171?pwd=T3JuWWZHbEdoeXlOaEZiaWczN1ZEZz09%20%20%D0%98%D0%B4%D0%B5%D0%BD%D1%82%D0%B8%D1%84%D0%B8%D0%BA%D0%B0%D1%82%D0%BE%D1%80%20%D0%BA%D0%BE%D0%BD%D1%84%D0%B5%D1%80%D0%B5%D0%BD%D1%86%D0%B8%D0%B8:%20853%206578%201171%20%D0%9A%D0%BE%D0%B4%20%D0%B4%D0%BE%D1%81%D1%82%D1%83%D0%BF%D0%B0:%20W7uRVR",
        "type": "lab",
        "isFirstWeek": true,
        "isSecondWeek": false,
        "isFirstSubgroup": true,
        "isSecondSubgroup": false,
        "day": 2,
        "number": 1
    },
    {
        "subject": "Маркетингові дослідження",
        "lecturer": "Капраль О.Р., ",
        "location": ", Лабораторна",
        "url": "https://us02web.zoom.us/j/85365781171?pwd=T3JuWWZHbEdoeXlOaEZiaWczN1ZEZz09%20%20%D0%98%D0%B4%D0%B5%D0%BD%D1%82%D0%B8%D1%84%D0%B8%D0%BA%D0%B0%D1%82%D0%BE%D1%80%20%D0%BA%D0%BE%D0%BD%D1%84%D0%B5%D1%80%D0%B5%D0%BD%D1%86%D0%B8%D0%B8:%20853%206578%201171%20%D0%9A%D0%BE%D0%B4%20%D0%B4%D0%BE%D1%81%D1%82%D1%83%D0%BF%D0%B0:%20W7uRVR",
        "type": "lab",
        "isFirstWeek": false,
        "isSecondWeek": true,
        "isFirstSubgroup": false,
        "isSecondSubgroup": true,
        "day": 2,
        "number": 1
    },
    {
        "subject": "Оподаткування зовнішньоекономічної діяльності",
        "lecturer": "Чиркова Ю.Л., ",
        "location": " Практична",
        "url": "https://teams.microsoft.com/l/message/19:4677ab92abe1401da6612754cac00fa8@thread.tacv2/1612965971660?tenantId=7631cd62-5187-4e15-8b8e-ef653e366e7a&groupId=42ba4bd5-c2be-4e30-96bd-1d9313569563&parentMessageId=1612965971660&teamName=%D0%9E%D0%BF%D0%BE%D0%B4%D0%B0%D1%82%D0%BA%D1%83%D0%B2%D0%B0%D0%BD%D0%BD%D1%8F%20%D0%97%D0%95%D0%94_%D0%9C%D0%95-37_%D0%9F%D1%80%D0%B0%D0%BA%D1%82%D0%B8%D1%87%D0%BD%D0%B5&channelName=%D0%97%D0%B0%D0%B3%D0%B0%D0%BB%D1%8C%D0%BD%D0%B5&createdTime=1612965971660",
        "type": "practical",
        "isFirstWeek": false,
        "isSecondWeek": true,
        "isFirstSubgroup": true,
        "isSecondSubgroup": true,
        "day": 2,
        "number": 2
    },
    {
        "subject": "Основи охорони праці та безпека життєдіяльності",
        "lecturer": "Корж Г.І., ",
        "location": " Практична",
        "url": "https://teams.microsoft.com/l/channel/19%3a6ec420815c58489c9e329c34b3d88c67%40thread.tacv2/General?groupId=178156d9-cd4b-42e3-9aab-d35ef4dceb39&tenantId=7631cd62-5187-4e15-8b8e-ef653e366e7a",
        "type": "practical",
        "isFirstWeek": true,
        "isSecondWeek": false,
        "isFirstSubgroup": true,
        "isSecondSubgroup": true,
        "day": 2,
        "number": 2
    },
    {
        "subject": "Управління експортно-імпортними операціями в умовах євроінтеграції",
        "lecturer": "Рудницька О.В., ",
        "location": " Лабораторна",
        "url": "https://zoom.us/j/96602611369?pwd=TmVOSC9Eam9EYXMyTHNFMkIvV2RvQT09",
        "type": "lab",
        "isFirstWeek": true,
        "isSecondWeek": true,
        "isFirstSubgroup": true,
        "isSecondSubgroup": false,
        "day": 2,
        "number": 3
    },
    {
        "subject": "Управління експортно-імпортними операціями в умовах євроінтеграції",
        "lecturer": "Рудницька О.В., ",
        "location": ", Лабораторна",
        "url": "https://zoom.us/j/94727798735?pwd=amVYenhUWjd6SmliYkptZzZiaWZNQT09",
        "type": "lab",
        "isFirstWeek": true,
        "isSecondWeek": true,
        "isFirstSubgroup": false,
        "isSecondSubgroup": true,
        "day": 2,
        "number": 4
    },
    {
        "subject": "Управління персоналом",
        "lecturer": "Гладун С.О., ",
        "location": " Практична",
        "url": "https://teams.microsoft.com/l/message/19:73d4cb7448ea425d8f0ccb9aed9777ee@thread.tacv2/1613131184022?tenantId=7631cd62-5187-4e15-8b8e-ef653e366e7a&groupId=52490f33-6290-4ade-9c2b-61f3eef5ecfe&parentMessageId=1613131184022&teamName=%D0%A3%D0%BF%D1%80%D0%B0%D0%B2%D0%BB%D1%96%D0%BD%D0%BD%D1%8F%20%D0%BF%D0%B5%D1%80%D1%81%D0%BE%D0%BD%D0%B0%D0%BB%D0%BE%D0%BC%20%D0%B3%D1%80.%20%D0%9C%D0%95%2020%2F21&channelName=%D0%A3%D0%9F%20%D0%9C%D0%95-37&createdTime=1613131184022",
        "type": "practical",
        "isFirstWeek": false,
        "isSecondWeek": true,
        "isFirstSubgroup": true,
        "isSecondSubgroup": true,
        "day": 3,
        "number": 3
    },
    {
        "subject": "Основи охорони праці та безпека життєдіяльності",
        "lecturer": "Корж Г.І., ",
        "location": " Лабораторна",
        "url": "https://teams.microsoft.com/l/channel/19%3a397c68f261dd4e30b95bacba121f661e%40thread.tacv2/%25D0%2597%25D0%25B0%25D0%25B3%25D0%25B0%25D0%25BB%25D1%258C%25D0%25BD%25D0%25B5?groupId=1ed411cf-bcf8-408e-ac02-5cf35d85b06f&tenantId=7631cd62-5187-4e15-8b8e-ef653e366e7a",
        "type": "lab",
        "isFirstWeek": true,
        "isSecondWeek": false,
        "isFirstSubgroup": true,
        "isSecondSubgroup": true,
        "day": 3,
        "number": 3
    },
    {
        "subject": "Маркетингові дослідження",
        "lecturer": "Лихолат С.М., ",
        "location": " Практична",
        "url": "https://us04web.zoom.us/j/76687202499?pwd=UW8yZ2lsU29UUUh6VEJacnYxQm15UT09",
        "type": "practical",
        "isFirstWeek": false,
        "isSecondWeek": true,
        "isFirstSubgroup": true,
        "isSecondSubgroup": true,
        "day": 3,
        "number": 4
    },
    {
        "subject": "Управління експортно-імпортними операціями в умовах євроінтеграції",
        "lecturer": "Двуліт З.П., ",
        "location": " Лекція",
        "url": "https://teams.microsoft.com/l/channel/19%3a9f617d7899694684a8016c82a7ade09b%40thread.tacv2/%25D0%2597%25D0%25B0%25D0%25B3%25D0%25B0%25D0%25BB%25D1%258C%25D0%25BD%25D0%25B5?groupId=88059262-068e-4371-a212-e9c9315727ef&tenantId=7631cd62-5187-4e15-8b8e-ef653e366e7a",
        "type": "lection",
        "isFirstWeek": true,
        "isSecondWeek": true,
        "isFirstSubgroup": true,
        "isSecondSubgroup": true,
        "day": 4,
        "number": 1
    },
    {
        "subject": "Основи охорони праці та безпека життєдіяльності",
        "lecturer": "Корж Г.І., ",
        "location": " Лекція",
        "url": "https://teams.microsoft.com/l/meetup-join/19%3a8e0345adbc56481e8a7c9666fa8917b5%40thread.tacv2/1616520476358?context=%7b%22Tid%22%3a%227631cd62-5187-4e15-8b8e-ef653e366e7a%22%2c%22Oid%22%3a%22969e6386-48c6-4f2f-a2ab-99358b0d01cf%22%7d",
        "type": "lection",
        "isFirstWeek": true,
        "isSecondWeek": true,
        "isFirstSubgroup": true,
        "isSecondSubgroup": true,
        "day": 4,
        "number": 2
    },
    {
        "subject": "Оподаткування зовнішньоекономічної діяльності",
        "lecturer": "Чиркова Ю.Л., ",
        "location": " Лекція",
        "url": "https://teams.microsoft.com/l/message/19:c184c4deb4e845d889b1c6e18f8549fa@thread.tacv2/1612867550809?tenantId=7631cd62-5187-4e15-8b8e-ef653e366e7a&groupId=c9cfe59b-51da-4256-b26a-a1dc25d5d93c&parentMessageId=1612867550809&teamName=%D0%9E%D0%9F%D0%9E%D0%94%D0%90%D0%A2%D0%9A%D0%A3%D0%92%D0%90%D0%9D%D0%9D%D0%AF%20%D0%97%D0%95%D0%94_%D0%9C%D0%95-35%2C36%2C37&channelName=%D0%97%D0%B0%D0%B3%D0%B0%D0%BB%D1%8C%D0%BD%D0%B5&createdTime=1612867550809",
        "type": "lection",
        "isFirstWeek": true,
        "isSecondWeek": true,
        "isFirstSubgroup": true,
        "isSecondSubgroup": true,
        "day": 4,
        "number": 4
    },
    {
        "subject": "Маркетингові дослідження",
        "lecturer": "Дмитрів А.Я., ",
        "location": " Лекція",
        "url": "https://teams.microsoft.com/_?tenantId=7631cd62-5187-4e15-8b8e-ef653e366e7a#/pre-join-calling/19:d6266f76450344d6ac589c7232bfedb2@thread.tacv2",
        "type": "lection",
        "isFirstWeek": true,
        "isSecondWeek": true,
        "isFirstSubgroup": true,
        "isSecondSubgroup": true,
        "day": 5,
        "number": 2
    },
    {
        "subject": "Управління персоналом",
        "lecturer": "Винничук Р.О., ",
        "location": " Лекція",
        "url": "https://us04web.zoom.us/j/4138639159?pwd=QWJuTlhOLzVSelRhNU9lTnFjSDhaUT09",
        "type": "lection",
        "isFirstWeek": true,
        "isSecondWeek": true,
        "isFirstSubgroup": true,
        "isSecondSubgroup": true,
        "day": 5,
        "number": 3
    }
]