[
    {
        "subject": "Конструкції будівель та споруд, частина 2",
        "lecturer": "Канюк В.М., ",
        "location": " Лекція",
        "url": "https://us04web.zoom.us/j/6878344359?pwd=SkFkcWtrZHJsT1ZseUFmUVEzSlBEQT09",
        "type": "lection",
        "isFirstWeek": true,
        "isSecondWeek": false,
        "isFirstSubgroup": true,
        "isSecondSubgroup": true,
        "day": 2,
        "number": 1
    },
    {
        "subject": "Конструкції будівель та споруд, частина 2",
        "lecturer": "Канюк В.М., ",
        "location": " Лекція",
        "url": "https://us04web.zoom.us/j/6878344359?pwd=SkFkcWtrZHJsT1ZseUFmUVEzSlBEQT09",
        "type": "lection",
        "isFirstWeek": true,
        "isSecondWeek": true,
        "isFirstSubgroup": true,
        "isSecondSubgroup": true,
        "day": 2,
        "number": 2
    },
    {
        "subject": "Теорія розвитку та припинення горіння",
        "lecturer": "Олійник Л.П., ",
        "location": " Лекція",
        "url": "https://teams.microsoft.com/l/team/19%3ac72a839e37dd4b77b3bbb1e3382965f0%40thread.tacv2/conversations?groupId=8d0af309-3067-4ac7-bafb-3bee4f47debc&tenantId=7631cd62-5187-4e15-8b8e-ef653e366e7a",
        "type": "lection",
        "isFirstWeek": true,
        "isSecondWeek": true,
        "isFirstSubgroup": true,
        "isSecondSubgroup": true,
        "day": 2,
        "number": 3
    },
    {
        "subject": "Будівельна механіка, частина 2",
        "lecturer": "Шиндер В.К., ",
        "location": " Лекція",
        "url": "https://teams.microsoft.com/l/meetup-join/19%3a4ccffad64ba444ccbb4c7dd14e17fbee%40thread.tacv2/1613144800141?context=%7b%22Tid%22%3a%227631cd62-5187-4e15-8b8e-ef653e366e7a%22%2c%22Oid%22%3a%22aa757a2f-7f39-4b6d-a15d-a1ca490019e6%22%7d",
        "type": "lection",
        "isFirstWeek": true,
        "isSecondWeek": true,
        "isFirstSubgroup": true,
        "isSecondSubgroup": true,
        "day": 2,
        "number": 4
    },
    {
        "subject": "Пожежна профілактика в будівництві",
        "lecturer": "Вашкевич Р.В., ",
        "location": " Практична",
        "url": "https://us02web.zoom.us/j/84010794624?pwd=NWhZa2RJK1M5UUJEOXQvdmZMK0NOUT09",
        "type": "practical",
        "isFirstWeek": true,
        "isSecondWeek": true,
        "isFirstSubgroup": true,
        "isSecondSubgroup": true,
        "day": 3,
        "number": 2
    },
    {
        "subject": "Теорія розвитку та припинення горіння",
        "lecturer": "Олійник Л.П., ",
        "location": " Лабораторна",
        "url": "https://teams.microsoft.com/l/team/19%3ac72a839e37dd4b77b3bbb1e3382965f0%40thread.tacv2/conversations?groupId=8d0af309-3067-4ac7-bafb-3bee4f47debc&tenantId=7631cd62-5187-4e15-8b8e-ef653e366e7a",
        "type": "lab",
        "isFirstWeek": true,
        "isSecondWeek": true,
        "isFirstSubgroup": true,
        "isSecondSubgroup": true,
        "day": 3,
        "number": 3
    },
    {
        "subject": "Будівельна механіка, частина 2",
        "lecturer": "Шиндер В.К., ",
        "location": " Практична",
        "url": "https://teams.microsoft.com/l/meetup-join/19%3a4ccffad64ba444ccbb4c7dd14e17fbee%40thread.tacv2/1613384132323?context=%7b%22Tid%22%3a%227631cd62-5187-4e15-8b8e-ef653e366e7a%22%2c%22Oid%22%3a%22aa757a2f-7f39-4b6d-a15d-a1ca490019e6%22%7d",
        "type": "practical",
        "isFirstWeek": true,
        "isSecondWeek": false,
        "isFirstSubgroup": true,
        "isSecondSubgroup": true,
        "day": 3,
        "number": 4
    },
    {
        "subject": "Теорія розвитку та припинення горіння",
        "lecturer": "Олійник Л.П., ",
        "location": " Практична",
        "url": "https://teams.microsoft.com/l/team/19%3ac72a839e37dd4b77b3bbb1e3382965f0%40thread.tacv2/conversations?groupId=8d0af309-3067-4ac7-bafb-3bee4f47debc&tenantId=7631cd62-5187-4e15-8b8e-ef653e366e7a",
        "type": "practical",
        "isFirstWeek": false,
        "isSecondWeek": true,
        "isFirstSubgroup": true,
        "isSecondSubgroup": true,
        "day": 3,
        "number": 4
    },
    {
        "subject": "Пожежна профілактика в будівництві",
        "lecturer": "Вашкевич Р.В., ",
        "location": " Лекція",
        "url": "https://us02web.zoom.us/j/85190843756?pwd=aUhKVUtMdGJrRkJhWE0rSnowVmMrQT09",
        "type": "lection",
        "isFirstWeek": false,
        "isSecondWeek": true,
        "isFirstSubgroup": true,
        "isSecondSubgroup": true,
        "day": 4,
        "number": 1
    },
    {
        "subject": "Пожежна профілактика в будівництві",
        "lecturer": "Вашкевич Р.В., ",
        "location": " Лекція",
        "url": "https://us02web.zoom.us/j/85338912826?pwd=Y1hDaityS1oxNlFpRVd2T21yK2x1dz09",
        "type": "lection",
        "isFirstWeek": true,
        "isSecondWeek": true,
        "isFirstSubgroup": true,
        "isSecondSubgroup": true,
        "day": 4,
        "number": 2
    },
    {
        "subject": "Методи досліджень вогнестійкості будівельних конструкцій",
        "lecturer": "Демчина Б.Г., ",
        "location": " Лекція",
        "url": "https://zoom.us/j/99174173585?pwd=Y2J1Ym5NbXl0UVd3MlJTaG9qVWIydz09",
        "type": "lection",
        "isFirstWeek": true,
        "isSecondWeek": true,
        "isFirstSubgroup": true,
        "isSecondSubgroup": true,
        "day": 4,
        "number": 3
    },
    {
        "subject": "Методи досліджень вогнестійкості будівельних конструкцій",
        "lecturer": "Пелех А.Б., ",
        "location": " Практична",
        "url": "https://us04web.zoom.us/j/2412820816?pwd=MVlCWFlYcWhNdlBEM3piS1lIMzQwUT09",
        "type": "practical",
        "isFirstWeek": true,
        "isSecondWeek": false,
        "isFirstSubgroup": true,
        "isSecondSubgroup": true,
        "day": 5,
        "number": 1
    },
    {
        "subject": "Методи досліджень вогнестійкості будівельних конструкцій",
        "lecturer": "Пелех А.Б., ",
        "location": " Лабораторна",
        "url": "",
        "type": "lab",
        "isFirstWeek": true,
        "isSecondWeek": true,
        "isFirstSubgroup": true,
        "isSecondSubgroup": true,
        "day": 5,
        "number": 2
    },
    {
        "subject": "Конструкції будівель та споруд, частина 2",
        "lecturer": "Канюк В.М., ",
        "location": " Практична",
        "url": "https://us04web.zoom.us/j/6878344359?pwd=SkFkcWtrZHJsT1ZseUFmUVEzSlBEQT09",
        "type": "practical",
        "isFirstWeek": true,
        "isSecondWeek": true,
        "isFirstSubgroup": true,
        "isSecondSubgroup": true,
        "day": 5,
        "number": 3
    }
]