[
    {
        "subject": "Біологія",
        "lecturer": "Вронська Н.Ю., ",
        "location": " Лекція",
        "url": "https://teams.microsoft.com/l/meetup-join/19%3a6d6d87c270554a91ba2eb1ce65de012e%40thread.tacv2/1612985325450?context=%7b%22Tid%22%3a%227631cd62-5187-4e15-8b8e-ef653e366e7a%22%2c%22Oid%22%3a%22baa770fc-2fc5-4099-9239-c17c2a855003%22%7d",
        "type": "lection",
        "isFirstWeek": true,
        "isSecondWeek": true,
        "isFirstSubgroup": true,
        "isSecondSubgroup": true,
        "day": 1,
        "number": 2
    },
    {
        "subject": "Загальна екологія і неоекологія",
        "lecturer": "Хомко Н.Ю., ",
        "location": " Лекція",
        "url": "https://teams.microsoft.com/l/team/19%3a704ecf62ecdf48ac8cb8bb1e64695b54%40thread.tacv2/conversations?groupId=5d0eee1e-77f1-4180-8b8e-882233219830&tenantId=7631cd62-5187-4e15-8b8e-ef653e366e7a",
        "type": "lection",
        "isFirstWeek": true,
        "isSecondWeek": true,
        "isFirstSubgroup": true,
        "isSecondSubgroup": true,
        "day": 1,
        "number": 3
    },
    {
        "subject": "Вища математика, частина 2",
        "lecturer": "Олексів І.Я., ",
        "location": " Лекція",
        "url": "https://us04web.zoom.us/j/72218320970?pwd=MTZsV3g4WjI3V2lRa3RsVUs5dkRvZz09",
        "type": "lection",
        "isFirstWeek": true,
        "isSecondWeek": true,
        "isFirstSubgroup": true,
        "isSecondSubgroup": true,
        "day": 1,
        "number": 4
    },
    {
        "subject": "Історія державності та культури України",
        "lecturer": "Шеломенцев-Терський С.В., ",
        "location": " Лекція",
        "url": "https://zoom.us/j/9641848736?pwd=S3N6NDRVbVpoNU92Y0ZCNnEwQUQ5Zz09",
        "type": "lection",
        "isFirstWeek": true,
        "isSecondWeek": false,
        "isFirstSubgroup": true,
        "isSecondSubgroup": true,
        "day": 1,
        "number": 5
    },
    {
        "subject": "Іноземна мова за професійним спрямуванням, частина 2",
        "lecturer": "Кушка Б.Г., ",
        "location": " Практична",
        "url": "https://teams.microsoft.com/l/meetup-join/19%3ameeting_MDA5YmY4MmUtNDBlMC00ZjQ1LWFjMzItZWUxMmI2N2FiMzJh%40thread.v2/0?context=%7b%22Tid%22%3a%227631cd62-5187-4e15-8b8e-ef653e366e7a%22%2c%22Oid%22%3a%2295ef99e2-c16d-42e6-a655-c4856f3256a0%22%7d",
        "type": "practical",
        "isFirstWeek": true,
        "isSecondWeek": true,
        "isFirstSubgroup": true,
        "isSecondSubgroup": true,
        "day": 2,
        "number": 1
    },
    {
        "subject": "Біологія",
        "lecturer": "Слюсар В.Т., ",
        "location": " Практична",
        "url": "https://teams.microsoft.com/l/meetup-join/19%3a28bb070cd0564f2a8f8124265e6756b1%40thread.tacv2/1613310385143?context=%7b%22Tid%22%3a%227631cd62-5187-4e15-8b8e-ef653e366e7a%22%2c%22Oid%22%3a%225f87dff0-60d4-42e7-bcfe-124a2777eda0%22%7d",
        "type": "practical",
        "isFirstWeek": true,
        "isSecondWeek": true,
        "isFirstSubgroup": true,
        "isSecondSubgroup": true,
        "day": 2,
        "number": 2
    },
    {
        "subject": "Біологія",
        "lecturer": "Слюсар В.Т., ",
        "location": " Лабораторна",
        "url": "https://teams.microsoft.com/l/meetup-join/19%3a28bb070cd0564f2a8f8124265e6756b1%40thread.tacv2/1613324198604?context=%7b%22Tid%22%3a%227631cd62-5187-4e15-8b8e-ef653e366e7a%22%2c%22Oid%22%3a%225f87dff0-60d4-42e7-bcfe-124a2777eda0%22%7d",
        "type": "lab",
        "isFirstWeek": true,
        "isSecondWeek": true,
        "isFirstSubgroup": true,
        "isSecondSubgroup": true,
        "day": 2,
        "number": 3
    },
    {
        "subject": "Інформатика",
        "lecturer": "Кузь О.Н., ",
        "location": " Лабораторна",
        "url": "https://us02web.zoom.us/j/84405809881?pwd=ZHdMVGt3NkRiNzd6VVRweFVrOHhRQT09",
        "type": "lab",
        "isFirstWeek": true,
        "isSecondWeek": true,
        "isFirstSubgroup": true,
        "isSecondSubgroup": true,
        "day": 2,
        "number": 4
    },
    {
        "subject": "Інформатика",
        "lecturer": "Кузь О.Н., ",
        "location": " Лабораторна",
        "url": "https://us02web.zoom.us/j/84405809881?pwd=ZHdMVGt3NkRiNzd6VVRweFVrOHhRQT09",
        "type": "lab",
        "isFirstWeek": true,
        "isSecondWeek": false,
        "isFirstSubgroup": true,
        "isSecondSubgroup": true,
        "day": 2,
        "number": 5
    },
    {
        "subject": "Загальна екологія і неоекологія",
        "lecturer": "Хомко Н.Ю., ",
        "location": " Лекція",
        "url": "https://teams.microsoft.com/l/team/19%3a704ecf62ecdf48ac8cb8bb1e64695b54%40thread.tacv2/conversations?groupId=5d0eee1e-77f1-4180-8b8e-882233219830&tenantId=7631cd62-5187-4e15-8b8e-ef653e366e7a",
        "type": "lection",
        "isFirstWeek": true,
        "isSecondWeek": true,
        "isFirstSubgroup": true,
        "isSecondSubgroup": true,
        "day": 3,
        "number": 2
    },
    {
        "subject": "Інформатика",
        "lecturer": "Кузь О.Н., ",
        "location": " Лекція",
        "url": "https://us02web.zoom.us/j/84405809881?pwd=ZHdMVGt3NkRiNzd6VVRweFVrOHhRQT09",
        "type": "lection",
        "isFirstWeek": true,
        "isSecondWeek": true,
        "isFirstSubgroup": true,
        "isSecondSubgroup": true,
        "day": 3,
        "number": 3
    },
    {
        "subject": "Вища математика, частина 2",
        "lecturer": "Олексів І.Я., ",
        "location": " Практична",
        "url": "https://us04web.zoom.us/j/72218320970?pwd=MTZsV3g4WjI3V2lRa3RsVUs5dkRvZz09",
        "type": "practical",
        "isFirstWeek": true,
        "isSecondWeek": true,
        "isFirstSubgroup": true,
        "isSecondSubgroup": true,
        "day": 4,
        "number": 2
    },
    {
        "subject": "Історія державності та культури України",
        "lecturer": "Хома І.Я., ",
        "location": " Практична",
        "url": "https://zoom.us/j/7085646391?pwd=VDQwVW9lRWw2V1lHbU4xb2NLQ3QxUT09%20%20Meeting%20ID:%20708%20564%206391%20Passcode:%20pXVnw2",
        "type": "practical",
        "isFirstWeek": true,
        "isSecondWeek": true,
        "isFirstSubgroup": true,
        "isSecondSubgroup": true,
        "day": 4,
        "number": 3
    },
    {
        "subject": "Фізичне виховання, частина 2",
        "lecturer": "Стадник В.В., 8-00  9-30 хлопці корп 21 вулСамчука 11",
        "location": " Практична",
        "url": "",
        "type": "practical",
        "isFirstWeek": true,
        "isSecondWeek": true,
        "isFirstSubgroup": true,
        "isSecondSubgroup": false,
        "day": 5,
        "number": 1
    },
    {
        "subject": "Фізичне виховання, частина 2",
        "lecturer": "Рожко О.І., 8-00  9-30 дівчата корп 21 вулСамчука 11",
        "location": ", Практична",
        "url": "",
        "type": "practical",
        "isFirstWeek": true,
        "isSecondWeek": true,
        "isFirstSubgroup": false,
        "isSecondSubgroup": true,
        "day": 5,
        "number": 1
    },
    {
        "subject": "Загальна екологія і неоекологія",
        "lecturer": "Шибанова А.М., ",
        "location": " Практична",
        "url": "https://zoom.us/j/99928878320?pwd=UTJxNXRjRDMzYWhrRjdQclBTcUVDQT09",
        "type": "practical",
        "isFirstWeek": true,
        "isSecondWeek": true,
        "isFirstSubgroup": true,
        "isSecondSubgroup": true,
        "day": 5,
        "number": 2
    },
    {
        "subject": "Загальна екологія і неоекологія",
        "lecturer": "Шибанова А.М., ",
        "location": " Практична",
        "url": "https://zoom.us/j/97905019257?pwd=cVhZS25iREc5UHlsTDdmNGZVQlI3dz09",
        "type": "practical",
        "isFirstWeek": true,
        "isSecondWeek": true,
        "isFirstSubgroup": true,
        "isSecondSubgroup": true,
        "day": 5,
        "number": 3
    }
]